maskit/__init__.py
maskit/_masked_circuits.py
maskit/_masks.py
maskit/circuits.py
maskit/ensembles.py
maskit/log_results.py
maskit/masks.py
maskit/optimizers.py
maskit/plotting.py
maskit/utils.py
maskit/datasets/__init__.py
maskit/datasets/circles.py
maskit/datasets/iris.py
maskit/datasets/mnist.py
maskit/datasets/utils.py
maskit-0.1.0.dist-info/LICENSE
maskit-0.1.0.dist-info/WHEEL
maskit-0.1.0.dist-info/METADATA
maskit-0.1.0.dist-info/RECORD
