Metadata-Version: 2.1
Name: maskit
Version: 0.1.0
Summary: Python package to explore masking gates in variational circuits
Keywords: quantum computing
Author-email: Eileen Kuehn <eileen.kuehn@kit.edu>, Christof Wendenius <christof.wendenius@kit.edu>
Requires-Python: >=3.7
Classifier: License :: OSI Approved :: MIT License
Requires-Dist: pennylane ~= 0.23
Requires-Dist: typing_extensions
Requires-Dist: tensorflow >=2.0.0 ; extra == "datasets"
Requires-Dist: scikit-learn ; extra == "datasets"
Requires-Dist: pre-commit ; extra == "dev"
Requires-Dist: change-log ; extra == "dev"
Requires-Dist: sphinx ; extra == "doc"
Requires-Dist: myst-parser ; extra == "doc"
Requires-Dist: pytest >=4.3.0 ; extra == "test"
Requires-Dist: flake8 ; extra == "test"
Requires-Dist: flake8-bugbear ; extra == "test"
Requires-Dist: black ; extra == "test"
Requires-Dist: scikit-learn ; extra == "test"
Requires-Dist: tensorflow >=2.0.0 ; extra == "test"
Project-URL: Source, https://github.com/cirKITers/masKIT
Provides-Extra: datasets
Provides-Extra: dev
Provides-Extra: doc
Provides-Extra: test
